[{"_path":"/speakers/bertram_gilfoyle","_dir":"speakers","_draft":false,"_partial":false,"_locale":"","_empty":true,"title":"BertramGilfoyle","description":"Software Architect","name":"Bertram Gilfoyle","img":"https://didukhn.github.io/homepage/assets/img/photo.jpg","body":{"type":"root","children":[],"toc":{"title":"","searchDepth":2,"depth":2,"links":[]}},"_type":"markdown","_id":"content:speakers:bertram_gilfoyle.md","_source":"content","_file":"speakers/bertram_gilfoyle.md","_extension":"md"},{"_path":"/speakers/brown_emmet","_dir":"speakers","_draft":false,"_partial":false,"_locale":"","_empty":true,"title":"BrownEmmet","description":"Time machine inventor","img":"https://cdnb.artstation.com/p/assets/images/images/012/528/275/large/salem-al-langawi-web.jpg?1535242546","name":"Dr. Emmett Brown","body":{"type":"root","children":[],"toc":{"title":"","searchDepth":2,"depth":2,"links":[]}},"_type":"markdown","_id":"content:speakers:brown_emmet.md","_source":"content","_file":"speakers/brown_emmet.md","_extension":"md"},{"_path":"/speakers/darth_vader","_dir":"speakers","_draft":false,"_partial":false,"_locale":"","_empty":true,"title":"DarthVader","description":"Lord Sith, Death Start CEO","img":"https://media.revistagq.com/photos/62a0a996223a33e985e4d59a/4:3/w_1199,h_899,c_limit/1072434_110615-cc-Darth-Vader-Thumb.jpg","name":"Darth Vader","body":{"type":"root","children":[],"toc":{"title":"","searchDepth":2,"depth":2,"links":[]}},"_type":"markdown","_id":"content:speakers:darth_vader.md","_source":"content","_file":"speakers/darth_vader.md","_extension":"md"},{"_path":"/speakers/gavin_belson","_dir":"speakers","_draft":false,"_partial":false,"_locale":"","_empty":true,"title":"GavinBelson","description":"Hoolie CEO","name":"Gavin Belson","img":"https://pbs.twimg.com/profile_images/731951677859868674/2iRz4Ikp_400x400.jpg","body":{"type":"root","children":[],"toc":{"title":"","searchDepth":2,"depth":2,"links":[]}},"_type":"markdown","_id":"content:speakers:gavin_belson.md","_source":"content","_file":"speakers/gavin_belson.md","_extension":"md"},{"_path":"/speakers/jinx","_dir":"speakers","_draft":false,"_partial":false,"_locale":"","_empty":true,"title":"Jinx","description":"Cute random cat","name":"Mr. Jinx","img":"https://cataas.com/cat","body":{"type":"root","children":[],"toc":{"title":"","searchDepth":2,"depth":2,"links":[]}},"_type":"markdown","_id":"content:speakers:Jinx.md","_source":"content","_file":"speakers/Jinx.md","_extension":"md"},{"_path":"/speakers/richard_hendricks","_dir":"speakers","_draft":false,"_partial":false,"_locale":"","_empty":true,"title":"RichardHendricks","description":"Pied Piper CEO","name":"Richard Hendricks","img":"https://tii.imgix.net/production/articles/4151/a093ce87-e9c9-4535-902f-353eafb3c5f7.jpeg?fm=jpeg&auto=compress&w=1600&h=900","body":{"type":"root","children":[],"toc":{"title":"","searchDepth":2,"depth":2,"links":[]}},"_type":"markdown","_id":"content:speakers:richard_hendricks.md","_source":"content","_file":"speakers/richard_hendricks.md","_extension":"md"}]